[{"name":"cult_info_page","qualifiedName":"cult_info_page","href":"ui_cult_info_page/ui_cult_info_page-library.html","type":"library","overriddenDepth":0,"packageName":"chico_dagua"},{"name":"CultInfoPage","qualifiedName":"cult_info_page.CultInfoPage","href":"ui_cult_info_page/CultInfoPage-class.html","type":"class","overriddenDepth":0,"packageName":"chico_dagua","enclosedBy":{"name":"cult_info_page","type":"library"}},{"name":"operator ==","qualifiedName":"cult_info_page.CultInfoPage.==","href":"ui_cult_info_page/CultInfoPage/operator_equals.html","type":"method","overriddenDepth":1,"packageName":"chico_dagua","enclosedBy":{"name":"CultInfoPage","type":"class"}},{"name":"CultInfoPage","qualifiedName":"cult_info_page.CultInfoPage.CultInfoPage","href":"ui_cult_info_page/CultInfoPage/CultInfoPage.html","type":"constructor","overriddenDepth":0,"packageName":"chico_dagua","enclosedBy":{"name":"CultInfoPage","type":"class"}},{"name":"build","qualifiedName":"cult_info_page.CultInfoPage.build","href":"ui_cult_info_page/CultInfoPage/build.html","type":"method","overriddenDepth":1,"packageName":"chico_dagua","enclosedBy":{"name":"CultInfoPage","type":"class"}},{"name":"createElement","qualifiedName":"cult_info_page.CultInfoPage.createElement","href":"ui_cult_info_page/CultInfoPage/createElement.html","type":"method","overriddenDepth":1,"packageName":"chico_dagua","enclosedBy":{"name":"CultInfoPage","type":"class"}},{"name":"debugDescribeChildren","qualifiedName":"cult_info_page.CultInfoPage.debugDescribeChildren","href":"ui_cult_info_page/CultInfoPage/debugDescribeChildren.html","type":"method","overriddenDepth":0,"packageName":"chico_dagua","enclosedBy":{"name":"CultInfoPage","type":"class"}},{"name":"debugFillProperties","qualifiedName":"cult_info_page.CultInfoPage.debugFillProperties","href":"ui_cult_info_page/CultInfoPage/debugFillProperties.html","type":"method","overriddenDepth":1,"packageName":"chico_dagua","enclosedBy":{"name":"CultInfoPage","type":"class"}},{"name":"hashCode","qualifiedName":"cult_info_page.CultInfoPage.hashCode","href":"ui_cult_info_page/CultInfoPage/hashCode.html","type":"property","overriddenDepth":0,"packageName":"chico_dagua","enclosedBy":{"name":"CultInfoPage","type":"class"}},{"name":"key","qualifiedName":"cult_info_page.CultInfoPage.key","href":"ui_cult_info_page/CultInfoPage/key.html","type":"property","overriddenDepth":0,"packageName":"chico_dagua","enclosedBy":{"name":"CultInfoPage","type":"class"}},{"name":"toDiagnosticsNode","qualifiedName":"cult_info_page.CultInfoPage.toDiagnosticsNode","href":"ui_cult_info_page/CultInfoPage/toDiagnosticsNode.html","type":"method","overriddenDepth":1,"packageName":"chico_dagua","enclosedBy":{"name":"CultInfoPage","type":"class"}},{"name":"toString","qualifiedName":"cult_info_page.CultInfoPage.toString","href":"ui_cult_info_page/CultInfoPage/toString.html","type":"method","overriddenDepth":1,"packageName":"chico_dagua","enclosedBy":{"name":"CultInfoPage","type":"class"}},{"name":"toStringDeep","qualifiedName":"cult_info_page.CultInfoPage.toStringDeep","href":"ui_cult_info_page/CultInfoPage/toStringDeep.html","type":"method","overriddenDepth":0,"packageName":"chico_dagua","enclosedBy":{"name":"CultInfoPage","type":"class"}},{"name":"toStringShallow","qualifiedName":"cult_info_page.CultInfoPage.toStringShallow","href":"ui_cult_info_page/CultInfoPage/toStringShallow.html","type":"method","overriddenDepth":0,"packageName":"chico_dagua","enclosedBy":{"name":"CultInfoPage","type":"class"}},{"name":"toStringShort","qualifiedName":"cult_info_page.CultInfoPage.toStringShort","href":"ui_cult_info_page/CultInfoPage/toStringShort.html","type":"method","overriddenDepth":2,"packageName":"chico_dagua","enclosedBy":{"name":"CultInfoPage","type":"class"}},{"name":"cult_query","qualifiedName":"cult_query","href":"ui_initial_flow_cult_query/ui_initial_flow_cult_query-library.html","type":"library","overriddenDepth":0,"packageName":"chico_dagua"},{"name":"CultQuery","qualifiedName":"cult_query.CultQuery","href":"ui_initial_flow_cult_query/CultQuery-class.html","type":"class","overriddenDepth":0,"packageName":"chico_dagua","enclosedBy":{"name":"cult_query","type":"library"}},{"name":"operator ==","qualifiedName":"cult_query.CultQuery.==","href":"ui_initial_flow_cult_query/CultQuery/operator_equals.html","type":"method","overriddenDepth":1,"packageName":"chico_dagua","enclosedBy":{"name":"CultQuery","type":"class"}},{"name":"CultQuery","qualifiedName":"cult_query.CultQuery.CultQuery","href":"ui_initial_flow_cult_query/CultQuery/CultQuery.html","type":"constructor","overriddenDepth":0,"packageName":"chico_dagua","enclosedBy":{"name":"CultQuery","type":"class"}},{"name":"createElement","qualifiedName":"cult_query.CultQuery.createElement","href":"ui_initial_flow_cult_query/CultQuery/createElement.html","type":"method","overriddenDepth":1,"packageName":"chico_dagua","enclosedBy":{"name":"CultQuery","type":"class"}},{"name":"createState","qualifiedName":"cult_query.CultQuery.createState","href":"ui_initial_flow_cult_query/CultQuery/createState.html","type":"method","overriddenDepth":1,"packageName":"chico_dagua","enclosedBy":{"name":"CultQuery","type":"class"}},{"name":"debugDescribeChildren","qualifiedName":"cult_query.CultQuery.debugDescribeChildren","href":"ui_initial_flow_cult_query/CultQuery/debugDescribeChildren.html","type":"method","overriddenDepth":0,"packageName":"chico_dagua","enclosedBy":{"name":"CultQuery","type":"class"}},{"name":"debugFillProperties","qualifiedName":"cult_query.CultQuery.debugFillProperties","href":"ui_initial_flow_cult_query/CultQuery/debugFillProperties.html","type":"method","overriddenDepth":1,"packageName":"chico_dagua","enclosedBy":{"name":"CultQuery","type":"class"}},{"name":"hashCode","qualifiedName":"cult_query.CultQuery.hashCode","href":"ui_initial_flow_cult_query/CultQuery/hashCode.html","type":"property","overriddenDepth":0,"packageName":"chico_dagua","enclosedBy":{"name":"CultQuery","type":"class"}},{"name":"key","qualifiedName":"cult_query.CultQuery.key","href":"ui_initial_flow_cult_query/CultQuery/key.html","type":"property","overriddenDepth":0,"packageName":"chico_dagua","enclosedBy":{"name":"CultQuery","type":"class"}},{"name":"toDiagnosticsNode","qualifiedName":"cult_query.CultQuery.toDiagnosticsNode","href":"ui_initial_flow_cult_query/CultQuery/toDiagnosticsNode.html","type":"method","overriddenDepth":1,"packageName":"chico_dagua","enclosedBy":{"name":"CultQuery","type":"class"}},{"name":"toString","qualifiedName":"cult_query.CultQuery.toString","href":"ui_initial_flow_cult_query/CultQuery/toString.html","type":"method","overriddenDepth":1,"packageName":"chico_dagua","enclosedBy":{"name":"CultQuery","type":"class"}},{"name":"toStringDeep","qualifiedName":"cult_query.CultQuery.toStringDeep","href":"ui_initial_flow_cult_query/CultQuery/toStringDeep.html","type":"method","overriddenDepth":0,"packageName":"chico_dagua","enclosedBy":{"name":"CultQuery","type":"class"}},{"name":"toStringShallow","qualifiedName":"cult_query.CultQuery.toStringShallow","href":"ui_initial_flow_cult_query/CultQuery/toStringShallow.html","type":"method","overriddenDepth":0,"packageName":"chico_dagua","enclosedBy":{"name":"CultQuery","type":"class"}},{"name":"toStringShort","qualifiedName":"cult_query.CultQuery.toStringShort","href":"ui_initial_flow_cult_query/CultQuery/toStringShort.html","type":"method","overriddenDepth":2,"packageName":"chico_dagua","enclosedBy":{"name":"CultQuery","type":"class"}},{"name":"cult_select_page","qualifiedName":"cult_select_page","href":"ui_cult_select_page/ui_cult_select_page-library.html","type":"library","overriddenDepth":0,"packageName":"chico_dagua"},{"name":"CultSelectPage","qualifiedName":"cult_select_page.CultSelectPage","href":"ui_cult_select_page/CultSelectPage-class.html","type":"class","overriddenDepth":0,"packageName":"chico_dagua","enclosedBy":{"name":"cult_select_page","type":"library"}},{"name":"operator ==","qualifiedName":"cult_select_page.CultSelectPage.==","href":"ui_cult_select_page/CultSelectPage/operator_equals.html","type":"method","overriddenDepth":1,"packageName":"chico_dagua","enclosedBy":{"name":"CultSelectPage","type":"class"}},{"name":"CultSelectPage","qualifiedName":"cult_select_page.CultSelectPage.CultSelectPage","href":"ui_cult_select_page/CultSelectPage/CultSelectPage.html","type":"constructor","overriddenDepth":0,"packageName":"chico_dagua","enclosedBy":{"name":"CultSelectPage","type":"class"}},{"name":"createElement","qualifiedName":"cult_select_page.CultSelectPage.createElement","href":"ui_cult_select_page/CultSelectPage/createElement.html","type":"method","overriddenDepth":1,"packageName":"chico_dagua","enclosedBy":{"name":"CultSelectPage","type":"class"}},{"name":"createState","qualifiedName":"cult_select_page.CultSelectPage.createState","href":"ui_cult_select_page/CultSelectPage/createState.html","type":"method","overriddenDepth":1,"packageName":"chico_dagua","enclosedBy":{"name":"CultSelectPage","type":"class"}},{"name":"debugDescribeChildren","qualifiedName":"cult_select_page.CultSelectPage.debugDescribeChildren","href":"ui_cult_select_page/CultSelectPage/debugDescribeChildren.html","type":"method","overriddenDepth":0,"packageName":"chico_dagua","enclosedBy":{"name":"CultSelectPage","type":"class"}},{"name":"debugFillProperties","qualifiedName":"cult_select_page.CultSelectPage.debugFillProperties","href":"ui_cult_select_page/CultSelectPage/debugFillProperties.html","type":"method","overriddenDepth":1,"packageName":"chico_dagua","enclosedBy":{"name":"CultSelectPage","type":"class"}},{"name":"hashCode","qualifiedName":"cult_select_page.CultSelectPage.hashCode","href":"ui_cult_select_page/CultSelectPage/hashCode.html","type":"property","overriddenDepth":0,"packageName":"chico_dagua","enclosedBy":{"name":"CultSelectPage","type":"class"}},{"name":"key","qualifiedName":"cult_select_page.CultSelectPage.key","href":"ui_cult_select_page/CultSelectPage/key.html","type":"property","overriddenDepth":0,"packageName":"chico_dagua","enclosedBy":{"name":"CultSelectPage","type":"class"}},{"name":"toDiagnosticsNode","qualifiedName":"cult_select_page.CultSelectPage.toDiagnosticsNode","href":"ui_cult_select_page/CultSelectPage/toDiagnosticsNode.html","type":"method","overriddenDepth":1,"packageName":"chico_dagua","enclosedBy":{"name":"CultSelectPage","type":"class"}},{"name":"toString","qualifiedName":"cult_select_page.CultSelectPage.toString","href":"ui_cult_select_page/CultSelectPage/toString.html","type":"method","overriddenDepth":1,"packageName":"chico_dagua","enclosedBy":{"name":"CultSelectPage","type":"class"}},{"name":"toStringDeep","qualifiedName":"cult_select_page.CultSelectPage.toStringDeep","href":"ui_cult_select_page/CultSelectPage/toStringDeep.html","type":"method","overriddenDepth":0,"packageName":"chico_dagua","enclosedBy":{"name":"CultSelectPage","type":"class"}},{"name":"toStringShallow","qualifiedName":"cult_select_page.CultSelectPage.toStringShallow","href":"ui_cult_select_page/CultSelectPage/toStringShallow.html","type":"method","overriddenDepth":0,"packageName":"chico_dagua","enclosedBy":{"name":"CultSelectPage","type":"class"}},{"name":"toStringShort","qualifiedName":"cult_select_page.CultSelectPage.toStringShort","href":"ui_cult_select_page/CultSelectPage/toStringShort.html","type":"method","overriddenDepth":2,"packageName":"chico_dagua","enclosedBy":{"name":"CultSelectPage","type":"class"}},{"name":"data_stuff","qualifiedName":"data_stuff","href":"aux_data_stuff/aux_data_stuff-library.html","type":"library","overriddenDepth":0,"packageName":"chico_dagua"},{"name":"DataStuff","qualifiedName":"data_stuff.DataStuff","href":"aux_data_stuff/DataStuff-class.html","type":"class","overriddenDepth":0,"packageName":"chico_dagua","enclosedBy":{"name":"data_stuff","type":"library"}},{"name":"DataStuff","qualifiedName":"data_stuff.DataStuff.DataStuff","href":"aux_data_stuff/DataStuff/DataStuff.html","type":"constructor","overriddenDepth":0,"packageName":"chico_dagua","enclosedBy":{"name":"DataStuff","type":"class"}},{"name":"clearHistory","qualifiedName":"data_stuff.DataStuff.clearHistory","href":"aux_data_stuff/DataStuff/clearHistory.html","type":"method","overriddenDepth":0,"packageName":"chico_dagua","enclosedBy":{"name":"DataStuff","type":"class"}},{"name":"dt","qualifiedName":"data_stuff.DataStuff.dt","href":"aux_data_stuff/DataStuff/dt.html","type":"property","overriddenDepth":0,"packageName":"chico_dagua","enclosedBy":{"name":"DataStuff","type":"class"}},{"name":"getAllCftsCity","qualifiedName":"data_stuff.DataStuff.getAllCftsCity","href":"aux_data_stuff/DataStuff/getAllCftsCity.html","type":"method","overriddenDepth":0,"packageName":"chico_dagua","enclosedBy":{"name":"DataStuff","type":"class"}},{"name":"getCfts","qualifiedName":"data_stuff.DataStuff.getCfts","href":"aux_data_stuff/DataStuff/getCfts.html","type":"method","overriddenDepth":0,"packageName":"chico_dagua","enclosedBy":{"name":"DataStuff","type":"class"}},{"name":"getCityId","qualifiedName":"data_stuff.DataStuff.getCityId","href":"aux_data_stuff/DataStuff/getCityId.html","type":"method","overriddenDepth":0,"packageName":"chico_dagua","enclosedBy":{"name":"DataStuff","type":"class"}},{"name":"getCityKeys","qualifiedName":"data_stuff.DataStuff.getCityKeys","href":"aux_data_stuff/DataStuff/getCityKeys.html","type":"method","overriddenDepth":0,"packageName":"chico_dagua","enclosedBy":{"name":"DataStuff","type":"class"}},{"name":"getCityName","qualifiedName":"data_stuff.DataStuff.getCityName","href":"aux_data_stuff/DataStuff/getCityName.html","type":"method","overriddenDepth":0,"packageName":"chico_dagua","enclosedBy":{"name":"DataStuff","type":"class"}},{"name":"getCultId","qualifiedName":"data_stuff.DataStuff.getCultId","href":"aux_data_stuff/DataStuff/getCultId.html","type":"method","overriddenDepth":0,"packageName":"chico_dagua","enclosedBy":{"name":"DataStuff","type":"class"}},{"name":"getCultKc","qualifiedName":"data_stuff.DataStuff.getCultKc","href":"aux_data_stuff/DataStuff/getCultKc.html","type":"method","overriddenDepth":0,"packageName":"chico_dagua","enclosedBy":{"name":"DataStuff","type":"class"}},{"name":"getCultKeys","qualifiedName":"data_stuff.DataStuff.getCultKeys","href":"aux_data_stuff/DataStuff/getCultKeys.html","type":"method","overriddenDepth":0,"packageName":"chico_dagua","enclosedBy":{"name":"DataStuff","type":"class"}},{"name":"getCultName","qualifiedName":"data_stuff.DataStuff.getCultName","href":"aux_data_stuff/DataStuff/getCultName.html","type":"method","overriddenDepth":0,"packageName":"chico_dagua","enclosedBy":{"name":"DataStuff","type":"class"}},{"name":"getDefaultCfts","qualifiedName":"data_stuff.DataStuff.getDefaultCfts","href":"aux_data_stuff/DataStuff/getDefaultCfts.html","type":"method","overriddenDepth":0,"packageName":"chico_dagua","enclosedBy":{"name":"DataStuff","type":"class"}},{"name":"getDirectory","qualifiedName":"data_stuff.DataStuff.getDirectory","href":"aux_data_stuff/DataStuff/getDirectory.html","type":"method","overriddenDepth":0,"packageName":"chico_dagua","enclosedBy":{"name":"DataStuff","type":"class"}},{"name":"getFile","qualifiedName":"data_stuff.DataStuff.getFile","href":"aux_data_stuff/DataStuff/getFile.html","type":"method","overriddenDepth":0,"packageName":"chico_dagua","enclosedBy":{"name":"DataStuff","type":"class"}},{"name":"getStageId","qualifiedName":"data_stuff.DataStuff.getStageId","href":"aux_data_stuff/DataStuff/getStageId.html","type":"method","overriddenDepth":0,"packageName":"chico_dagua","enclosedBy":{"name":"DataStuff","type":"class"}},{"name":"getStageKeys","qualifiedName":"data_stuff.DataStuff.getStageKeys","href":"aux_data_stuff/DataStuff/getStageKeys.html","type":"method","overriddenDepth":0,"packageName":"chico_dagua","enclosedBy":{"name":"DataStuff","type":"class"}},{"name":"getStageName","qualifiedName":"data_stuff.DataStuff.getStageName","href":"aux_data_stuff/DataStuff/getStageName.html","type":"method","overriddenDepth":0,"packageName":"chico_dagua","enclosedBy":{"name":"DataStuff","type":"class"}},{"name":"hasBetterCfts","qualifiedName":"data_stuff.DataStuff.hasBetterCfts","href":"aux_data_stuff/DataStuff/hasBetterCfts.html","type":"method","overriddenDepth":0,"packageName":"chico_dagua","enclosedBy":{"name":"DataStuff","type":"class"}},{"name":"history","qualifiedName":"data_stuff.DataStuff.history","href":"aux_data_stuff/DataStuff/history.html","type":"property","overriddenDepth":0,"packageName":"chico_dagua","enclosedBy":{"name":"DataStuff","type":"class"}},{"name":"DataStuff.internal","qualifiedName":"data_stuff.DataStuff.internal","href":"aux_data_stuff/DataStuff/DataStuff.internal.html","type":"constructor","overriddenDepth":0,"packageName":"chico_dagua","enclosedBy":{"name":"DataStuff","type":"class"}},{"name":"readData","qualifiedName":"data_stuff.DataStuff.readData","href":"aux_data_stuff/DataStuff/readData.html","type":"method","overriddenDepth":0,"packageName":"chico_dagua","enclosedBy":{"name":"DataStuff","type":"class"}},{"name":"saveData","qualifiedName":"data_stuff.DataStuff.saveData","href":"aux_data_stuff/DataStuff/saveData.html","type":"method","overriddenDepth":0,"packageName":"chico_dagua","enclosedBy":{"name":"DataStuff","type":"class"}},{"name":"eto_page","qualifiedName":"eto_page","href":"ui_session_flow_eto_page/ui_session_flow_eto_page-library.html","type":"library","overriddenDepth":0,"packageName":"chico_dagua"},{"name":"EToPage","qualifiedName":"eto_page.EToPage","href":"ui_session_flow_eto_page/EToPage-class.html","type":"class","overriddenDepth":0,"packageName":"chico_dagua","enclosedBy":{"name":"eto_page","type":"library"}},{"name":"operator ==","qualifiedName":"eto_page.EToPage.==","href":"ui_session_flow_eto_page/EToPage/operator_equals.html","type":"method","overriddenDepth":1,"packageName":"chico_dagua","enclosedBy":{"name":"EToPage","type":"class"}},{"name":"EToPage","qualifiedName":"eto_page.EToPage.EToPage","href":"ui_session_flow_eto_page/EToPage/EToPage.html","type":"constructor","overriddenDepth":0,"packageName":"chico_dagua","enclosedBy":{"name":"EToPage","type":"class"}},{"name":"createElement","qualifiedName":"eto_page.EToPage.createElement","href":"ui_session_flow_eto_page/EToPage/createElement.html","type":"method","overriddenDepth":1,"packageName":"chico_dagua","enclosedBy":{"name":"EToPage","type":"class"}},{"name":"createState","qualifiedName":"eto_page.EToPage.createState","href":"ui_session_flow_eto_page/EToPage/createState.html","type":"method","overriddenDepth":1,"packageName":"chico_dagua","enclosedBy":{"name":"EToPage","type":"class"}},{"name":"debugDescribeChildren","qualifiedName":"eto_page.EToPage.debugDescribeChildren","href":"ui_session_flow_eto_page/EToPage/debugDescribeChildren.html","type":"method","overriddenDepth":0,"packageName":"chico_dagua","enclosedBy":{"name":"EToPage","type":"class"}},{"name":"debugFillProperties","qualifiedName":"eto_page.EToPage.debugFillProperties","href":"ui_session_flow_eto_page/EToPage/debugFillProperties.html","type":"method","overriddenDepth":1,"packageName":"chico_dagua","enclosedBy":{"name":"EToPage","type":"class"}},{"name":"hashCode","qualifiedName":"eto_page.EToPage.hashCode","href":"ui_session_flow_eto_page/EToPage/hashCode.html","type":"property","overriddenDepth":0,"packageName":"chico_dagua","enclosedBy":{"name":"EToPage","type":"class"}},{"name":"key","qualifiedName":"eto_page.EToPage.key","href":"ui_session_flow_eto_page/EToPage/key.html","type":"property","overriddenDepth":0,"packageName":"chico_dagua","enclosedBy":{"name":"EToPage","type":"class"}},{"name":"toDiagnosticsNode","qualifiedName":"eto_page.EToPage.toDiagnosticsNode","href":"ui_session_flow_eto_page/EToPage/toDiagnosticsNode.html","type":"method","overriddenDepth":1,"packageName":"chico_dagua","enclosedBy":{"name":"EToPage","type":"class"}},{"name":"toString","qualifiedName":"eto_page.EToPage.toString","href":"ui_session_flow_eto_page/EToPage/toString.html","type":"method","overriddenDepth":1,"packageName":"chico_dagua","enclosedBy":{"name":"EToPage","type":"class"}},{"name":"toStringDeep","qualifiedName":"eto_page.EToPage.toStringDeep","href":"ui_session_flow_eto_page/EToPage/toStringDeep.html","type":"method","overriddenDepth":0,"packageName":"chico_dagua","enclosedBy":{"name":"EToPage","type":"class"}},{"name":"toStringShallow","qualifiedName":"eto_page.EToPage.toStringShallow","href":"ui_session_flow_eto_page/EToPage/toStringShallow.html","type":"method","overriddenDepth":0,"packageName":"chico_dagua","enclosedBy":{"name":"EToPage","type":"class"}},{"name":"toStringShort","qualifiedName":"eto_page.EToPage.toStringShort","href":"ui_session_flow_eto_page/EToPage/toStringShort.html","type":"method","overriddenDepth":2,"packageName":"chico_dagua","enclosedBy":{"name":"EToPage","type":"class"}},{"name":"first_use_page","qualifiedName":"first_use_page","href":"ui_initial_flow_first_use_page/ui_initial_flow_first_use_page-library.html","type":"library","overriddenDepth":0,"packageName":"chico_dagua"},{"name":"FirstUsePage","qualifiedName":"first_use_page.FirstUsePage","href":"ui_initial_flow_first_use_page/FirstUsePage-class.html","type":"class","overriddenDepth":0,"packageName":"chico_dagua","enclosedBy":{"name":"first_use_page","type":"library"}},{"name":"operator ==","qualifiedName":"first_use_page.FirstUsePage.==","href":"ui_initial_flow_first_use_page/FirstUsePage/operator_equals.html","type":"method","overriddenDepth":1,"packageName":"chico_dagua","enclosedBy":{"name":"FirstUsePage","type":"class"}},{"name":"FirstUsePage","qualifiedName":"first_use_page.FirstUsePage.FirstUsePage","href":"ui_initial_flow_first_use_page/FirstUsePage/FirstUsePage.html","type":"constructor","overriddenDepth":0,"packageName":"chico_dagua","enclosedBy":{"name":"FirstUsePage","type":"class"}},{"name":"build","qualifiedName":"first_use_page.FirstUsePage.build","href":"ui_initial_flow_first_use_page/FirstUsePage/build.html","type":"method","overriddenDepth":1,"packageName":"chico_dagua","enclosedBy":{"name":"FirstUsePage","type":"class"}},{"name":"createElement","qualifiedName":"first_use_page.FirstUsePage.createElement","href":"ui_initial_flow_first_use_page/FirstUsePage/createElement.html","type":"method","overriddenDepth":1,"packageName":"chico_dagua","enclosedBy":{"name":"FirstUsePage","type":"class"}},{"name":"debugDescribeChildren","qualifiedName":"first_use_page.FirstUsePage.debugDescribeChildren","href":"ui_initial_flow_first_use_page/FirstUsePage/debugDescribeChildren.html","type":"method","overriddenDepth":0,"packageName":"chico_dagua","enclosedBy":{"name":"FirstUsePage","type":"class"}},{"name":"debugFillProperties","qualifiedName":"first_use_page.FirstUsePage.debugFillProperties","href":"ui_initial_flow_first_use_page/FirstUsePage/debugFillProperties.html","type":"method","overriddenDepth":1,"packageName":"chico_dagua","enclosedBy":{"name":"FirstUsePage","type":"class"}},{"name":"hashCode","qualifiedName":"first_use_page.FirstUsePage.hashCode","href":"ui_initial_flow_first_use_page/FirstUsePage/hashCode.html","type":"property","overriddenDepth":0,"packageName":"chico_dagua","enclosedBy":{"name":"FirstUsePage","type":"class"}},{"name":"key","qualifiedName":"first_use_page.FirstUsePage.key","href":"ui_initial_flow_first_use_page/FirstUsePage/key.html","type":"property","overriddenDepth":0,"packageName":"chico_dagua","enclosedBy":{"name":"FirstUsePage","type":"class"}},{"name":"toDiagnosticsNode","qualifiedName":"first_use_page.FirstUsePage.toDiagnosticsNode","href":"ui_initial_flow_first_use_page/FirstUsePage/toDiagnosticsNode.html","type":"method","overriddenDepth":1,"packageName":"chico_dagua","enclosedBy":{"name":"FirstUsePage","type":"class"}},{"name":"toString","qualifiedName":"first_use_page.FirstUsePage.toString","href":"ui_initial_flow_first_use_page/FirstUsePage/toString.html","type":"method","overriddenDepth":1,"packageName":"chico_dagua","enclosedBy":{"name":"FirstUsePage","type":"class"}},{"name":"toStringDeep","qualifiedName":"first_use_page.FirstUsePage.toStringDeep","href":"ui_initial_flow_first_use_page/FirstUsePage/toStringDeep.html","type":"method","overriddenDepth":0,"packageName":"chico_dagua","enclosedBy":{"name":"FirstUsePage","type":"class"}},{"name":"toStringShallow","qualifiedName":"first_use_page.FirstUsePage.toStringShallow","href":"ui_initial_flow_first_use_page/FirstUsePage/toStringShallow.html","type":"method","overriddenDepth":0,"packageName":"chico_dagua","enclosedBy":{"name":"FirstUsePage","type":"class"}},{"name":"toStringShort","qualifiedName":"first_use_page.FirstUsePage.toStringShort","href":"ui_initial_flow_first_use_page/FirstUsePage/toStringShort.html","type":"method","overriddenDepth":2,"packageName":"chico_dagua","enclosedBy":{"name":"FirstUsePage","type":"class"}},{"name":"flow_model","qualifiedName":"flow_model","href":"model_flow_model/model_flow_model-library.html","type":"library","overriddenDepth":0,"packageName":"chico_dagua"},{"name":"FlowModel","qualifiedName":"flow_model.FlowModel","href":"model_flow_model/FlowModel-class.html","type":"class","overriddenDepth":0,"packageName":"chico_dagua","enclosedBy":{"name":"flow_model","type":"library"}},{"name":"FlowModel","qualifiedName":"flow_model.FlowModel.FlowModel","href":"model_flow_model/FlowModel/FlowModel.html","type":"constructor","overriddenDepth":0,"packageName":"chico_dagua","enclosedBy":{"name":"FlowModel","type":"class"}},{"name":"et0","qualifiedName":"flow_model.FlowModel.et0","href":"model_flow_model/FlowModel/et0.html","type":"property","overriddenDepth":0,"packageName":"chico_dagua","enclosedBy":{"name":"FlowModel","type":"class"}},{"name":"etc","qualifiedName":"flow_model.FlowModel.etc","href":"model_flow_model/FlowModel/etc.html","type":"property","overriddenDepth":0,"packageName":"chico_dagua","enclosedBy":{"name":"FlowModel","type":"class"}},{"name":"kc","qualifiedName":"flow_model.FlowModel.kc","href":"model_flow_model/FlowModel/kc.html","type":"property","overriddenDepth":0,"packageName":"chico_dagua","enclosedBy":{"name":"FlowModel","type":"class"}},{"name":"of","qualifiedName":"flow_model.FlowModel.of","href":"model_flow_model/FlowModel/of.html","type":"method","overriddenDepth":0,"packageName":"chico_dagua","enclosedBy":{"name":"FlowModel","type":"class"}},{"name":"setEt0","qualifiedName":"flow_model.FlowModel.setEt0","href":"model_flow_model/FlowModel/setEt0.html","type":"method","overriddenDepth":0,"packageName":"chico_dagua","enclosedBy":{"name":"FlowModel","type":"class"}},{"name":"setEtc","qualifiedName":"flow_model.FlowModel.setEtc","href":"model_flow_model/FlowModel/setEtc.html","type":"method","overriddenDepth":0,"packageName":"chico_dagua","enclosedBy":{"name":"FlowModel","type":"class"}},{"name":"setKc","qualifiedName":"flow_model.FlowModel.setKc","href":"model_flow_model/FlowModel/setKc.html","type":"method","overriddenDepth":0,"packageName":"chico_dagua","enclosedBy":{"name":"FlowModel","type":"class"}},{"name":"setStage","qualifiedName":"flow_model.FlowModel.setStage","href":"model_flow_model/FlowModel/setStage.html","type":"method","overriddenDepth":0,"packageName":"chico_dagua","enclosedBy":{"name":"FlowModel","type":"class"}},{"name":"setTempMax","qualifiedName":"flow_model.FlowModel.setTempMax","href":"model_flow_model/FlowModel/setTempMax.html","type":"method","overriddenDepth":0,"packageName":"chico_dagua","enclosedBy":{"name":"FlowModel","type":"class"}},{"name":"setTempMin","qualifiedName":"flow_model.FlowModel.setTempMin","href":"model_flow_model/FlowModel/setTempMin.html","type":"method","overriddenDepth":0,"packageName":"chico_dagua","enclosedBy":{"name":"FlowModel","type":"class"}},{"name":"stage","qualifiedName":"flow_model.FlowModel.stage","href":"model_flow_model/FlowModel/stage.html","type":"property","overriddenDepth":0,"packageName":"chico_dagua","enclosedBy":{"name":"FlowModel","type":"class"}},{"name":"tempMax","qualifiedName":"flow_model.FlowModel.tempMax","href":"model_flow_model/FlowModel/tempMax.html","type":"property","overriddenDepth":0,"packageName":"chico_dagua","enclosedBy":{"name":"FlowModel","type":"class"}},{"name":"tempMin","qualifiedName":"flow_model.FlowModel.tempMin","href":"model_flow_model/FlowModel/tempMin.html","type":"property","overriddenDepth":0,"packageName":"chico_dagua","enclosedBy":{"name":"FlowModel","type":"class"}},{"name":"history_page","qualifiedName":"history_page","href":"ui_history_page/ui_history_page-library.html","type":"library","overriddenDepth":0,"packageName":"chico_dagua"},{"name":"HistoryPage","qualifiedName":"history_page.HistoryPage","href":"ui_history_page/HistoryPage-class.html","type":"class","overriddenDepth":0,"packageName":"chico_dagua","enclosedBy":{"name":"history_page","type":"library"}},{"name":"operator ==","qualifiedName":"history_page.HistoryPage.==","href":"ui_history_page/HistoryPage/operator_equals.html","type":"method","overriddenDepth":1,"packageName":"chico_dagua","enclosedBy":{"name":"HistoryPage","type":"class"}},{"name":"HistoryPage","qualifiedName":"history_page.HistoryPage.HistoryPage","href":"ui_history_page/HistoryPage/HistoryPage.html","type":"constructor","overriddenDepth":0,"packageName":"chico_dagua","enclosedBy":{"name":"HistoryPage","type":"class"}},{"name":"createElement","qualifiedName":"history_page.HistoryPage.createElement","href":"ui_history_page/HistoryPage/createElement.html","type":"method","overriddenDepth":1,"packageName":"chico_dagua","enclosedBy":{"name":"HistoryPage","type":"class"}},{"name":"createState","qualifiedName":"history_page.HistoryPage.createState","href":"ui_history_page/HistoryPage/createState.html","type":"method","overriddenDepth":1,"packageName":"chico_dagua","enclosedBy":{"name":"HistoryPage","type":"class"}},{"name":"debugDescribeChildren","qualifiedName":"history_page.HistoryPage.debugDescribeChildren","href":"ui_history_page/HistoryPage/debugDescribeChildren.html","type":"method","overriddenDepth":0,"packageName":"chico_dagua","enclosedBy":{"name":"HistoryPage","type":"class"}},{"name":"debugFillProperties","qualifiedName":"history_page.HistoryPage.debugFillProperties","href":"ui_history_page/HistoryPage/debugFillProperties.html","type":"method","overriddenDepth":1,"packageName":"chico_dagua","enclosedBy":{"name":"HistoryPage","type":"class"}},{"name":"hashCode","qualifiedName":"history_page.HistoryPage.hashCode","href":"ui_history_page/HistoryPage/hashCode.html","type":"property","overriddenDepth":0,"packageName":"chico_dagua","enclosedBy":{"name":"HistoryPage","type":"class"}},{"name":"key","qualifiedName":"history_page.HistoryPage.key","href":"ui_history_page/HistoryPage/key.html","type":"property","overriddenDepth":0,"packageName":"chico_dagua","enclosedBy":{"name":"HistoryPage","type":"class"}},{"name":"toDiagnosticsNode","qualifiedName":"history_page.HistoryPage.toDiagnosticsNode","href":"ui_history_page/HistoryPage/toDiagnosticsNode.html","type":"method","overriddenDepth":1,"packageName":"chico_dagua","enclosedBy":{"name":"HistoryPage","type":"class"}},{"name":"toString","qualifiedName":"history_page.HistoryPage.toString","href":"ui_history_page/HistoryPage/toString.html","type":"method","overriddenDepth":1,"packageName":"chico_dagua","enclosedBy":{"name":"HistoryPage","type":"class"}},{"name":"toStringDeep","qualifiedName":"history_page.HistoryPage.toStringDeep","href":"ui_history_page/HistoryPage/toStringDeep.html","type":"method","overriddenDepth":0,"packageName":"chico_dagua","enclosedBy":{"name":"HistoryPage","type":"class"}},{"name":"toStringShallow","qualifiedName":"history_page.HistoryPage.toStringShallow","href":"ui_history_page/HistoryPage/toStringShallow.html","type":"method","overriddenDepth":0,"packageName":"chico_dagua","enclosedBy":{"name":"HistoryPage","type":"class"}},{"name":"toStringShort","qualifiedName":"history_page.HistoryPage.toStringShort","href":"ui_history_page/HistoryPage/toStringShort.html","type":"method","overriddenDepth":2,"packageName":"chico_dagua","enclosedBy":{"name":"HistoryPage","type":"class"}},{"name":"home_page","qualifiedName":"home_page","href":"ui_home_page/ui_home_page-library.html","type":"library","overriddenDepth":0,"packageName":"chico_dagua"},{"name":"HomePage","qualifiedName":"home_page.HomePage","href":"ui_home_page/HomePage-class.html","type":"class","overriddenDepth":0,"packageName":"chico_dagua","enclosedBy":{"name":"home_page","type":"library"}},{"name":"operator ==","qualifiedName":"home_page.HomePage.==","href":"ui_home_page/HomePage/operator_equals.html","type":"method","overriddenDepth":1,"packageName":"chico_dagua","enclosedBy":{"name":"HomePage","type":"class"}},{"name":"HomePage","qualifiedName":"home_page.HomePage.HomePage","href":"ui_home_page/HomePage/HomePage.html","type":"constructor","overriddenDepth":0,"packageName":"chico_dagua","enclosedBy":{"name":"HomePage","type":"class"}},{"name":"createElement","qualifiedName":"home_page.HomePage.createElement","href":"ui_home_page/HomePage/createElement.html","type":"method","overriddenDepth":1,"packageName":"chico_dagua","enclosedBy":{"name":"HomePage","type":"class"}},{"name":"createState","qualifiedName":"home_page.HomePage.createState","href":"ui_home_page/HomePage/createState.html","type":"method","overriddenDepth":1,"packageName":"chico_dagua","enclosedBy":{"name":"HomePage","type":"class"}},{"name":"debugDescribeChildren","qualifiedName":"home_page.HomePage.debugDescribeChildren","href":"ui_home_page/HomePage/debugDescribeChildren.html","type":"method","overriddenDepth":0,"packageName":"chico_dagua","enclosedBy":{"name":"HomePage","type":"class"}},{"name":"debugFillProperties","qualifiedName":"home_page.HomePage.debugFillProperties","href":"ui_home_page/HomePage/debugFillProperties.html","type":"method","overriddenDepth":1,"packageName":"chico_dagua","enclosedBy":{"name":"HomePage","type":"class"}},{"name":"hashCode","qualifiedName":"home_page.HomePage.hashCode","href":"ui_home_page/HomePage/hashCode.html","type":"property","overriddenDepth":0,"packageName":"chico_dagua","enclosedBy":{"name":"HomePage","type":"class"}},{"name":"key","qualifiedName":"home_page.HomePage.key","href":"ui_home_page/HomePage/key.html","type":"property","overriddenDepth":0,"packageName":"chico_dagua","enclosedBy":{"name":"HomePage","type":"class"}},{"name":"toDiagnosticsNode","qualifiedName":"home_page.HomePage.toDiagnosticsNode","href":"ui_home_page/HomePage/toDiagnosticsNode.html","type":"method","overriddenDepth":1,"packageName":"chico_dagua","enclosedBy":{"name":"HomePage","type":"class"}},{"name":"toString","qualifiedName":"home_page.HomePage.toString","href":"ui_home_page/HomePage/toString.html","type":"method","overriddenDepth":1,"packageName":"chico_dagua","enclosedBy":{"name":"HomePage","type":"class"}},{"name":"toStringDeep","qualifiedName":"home_page.HomePage.toStringDeep","href":"ui_home_page/HomePage/toStringDeep.html","type":"method","overriddenDepth":0,"packageName":"chico_dagua","enclosedBy":{"name":"HomePage","type":"class"}},{"name":"toStringShallow","qualifiedName":"home_page.HomePage.toStringShallow","href":"ui_home_page/HomePage/toStringShallow.html","type":"method","overriddenDepth":0,"packageName":"chico_dagua","enclosedBy":{"name":"HomePage","type":"class"}},{"name":"toStringShort","qualifiedName":"home_page.HomePage.toStringShort","href":"ui_home_page/HomePage/toStringShort.html","type":"method","overriddenDepth":2,"packageName":"chico_dagua","enclosedBy":{"name":"HomePage","type":"class"}},{"name":"irr_query","qualifiedName":"irr_query","href":"ui_initial_flow_irr_query/ui_initial_flow_irr_query-library.html","type":"library","overriddenDepth":0,"packageName":"chico_dagua"},{"name":"IrrQuery","qualifiedName":"irr_query.IrrQuery","href":"ui_initial_flow_irr_query/IrrQuery-class.html","type":"class","overriddenDepth":0,"packageName":"chico_dagua","enclosedBy":{"name":"irr_query","type":"library"}},{"name":"operator ==","qualifiedName":"irr_query.IrrQuery.==","href":"ui_initial_flow_irr_query/IrrQuery/operator_equals.html","type":"method","overriddenDepth":1,"packageName":"chico_dagua","enclosedBy":{"name":"IrrQuery","type":"class"}},{"name":"IrrQuery","qualifiedName":"irr_query.IrrQuery.IrrQuery","href":"ui_initial_flow_irr_query/IrrQuery/IrrQuery.html","type":"constructor","overriddenDepth":0,"packageName":"chico_dagua","enclosedBy":{"name":"IrrQuery","type":"class"}},{"name":"createElement","qualifiedName":"irr_query.IrrQuery.createElement","href":"ui_initial_flow_irr_query/IrrQuery/createElement.html","type":"method","overriddenDepth":1,"packageName":"chico_dagua","enclosedBy":{"name":"IrrQuery","type":"class"}},{"name":"createState","qualifiedName":"irr_query.IrrQuery.createState","href":"ui_initial_flow_irr_query/IrrQuery/createState.html","type":"method","overriddenDepth":1,"packageName":"chico_dagua","enclosedBy":{"name":"IrrQuery","type":"class"}},{"name":"debugDescribeChildren","qualifiedName":"irr_query.IrrQuery.debugDescribeChildren","href":"ui_initial_flow_irr_query/IrrQuery/debugDescribeChildren.html","type":"method","overriddenDepth":0,"packageName":"chico_dagua","enclosedBy":{"name":"IrrQuery","type":"class"}},{"name":"debugFillProperties","qualifiedName":"irr_query.IrrQuery.debugFillProperties","href":"ui_initial_flow_irr_query/IrrQuery/debugFillProperties.html","type":"method","overriddenDepth":1,"packageName":"chico_dagua","enclosedBy":{"name":"IrrQuery","type":"class"}},{"name":"hashCode","qualifiedName":"irr_query.IrrQuery.hashCode","href":"ui_initial_flow_irr_query/IrrQuery/hashCode.html","type":"property","overriddenDepth":0,"packageName":"chico_dagua","enclosedBy":{"name":"IrrQuery","type":"class"}},{"name":"key","qualifiedName":"irr_query.IrrQuery.key","href":"ui_initial_flow_irr_query/IrrQuery/key.html","type":"property","overriddenDepth":0,"packageName":"chico_dagua","enclosedBy":{"name":"IrrQuery","type":"class"}},{"name":"toDiagnosticsNode","qualifiedName":"irr_query.IrrQuery.toDiagnosticsNode","href":"ui_initial_flow_irr_query/IrrQuery/toDiagnosticsNode.html","type":"method","overriddenDepth":1,"packageName":"chico_dagua","enclosedBy":{"name":"IrrQuery","type":"class"}},{"name":"toString","qualifiedName":"irr_query.IrrQuery.toString","href":"ui_initial_flow_irr_query/IrrQuery/toString.html","type":"method","overriddenDepth":1,"packageName":"chico_dagua","enclosedBy":{"name":"IrrQuery","type":"class"}},{"name":"toStringDeep","qualifiedName":"irr_query.IrrQuery.toStringDeep","href":"ui_initial_flow_irr_query/IrrQuery/toStringDeep.html","type":"method","overriddenDepth":0,"packageName":"chico_dagua","enclosedBy":{"name":"IrrQuery","type":"class"}},{"name":"toStringShallow","qualifiedName":"irr_query.IrrQuery.toStringShallow","href":"ui_initial_flow_irr_query/IrrQuery/toStringShallow.html","type":"method","overriddenDepth":0,"packageName":"chico_dagua","enclosedBy":{"name":"IrrQuery","type":"class"}},{"name":"toStringShort","qualifiedName":"irr_query.IrrQuery.toStringShort","href":"ui_initial_flow_irr_query/IrrQuery/toStringShort.html","type":"method","overriddenDepth":2,"packageName":"chico_dagua","enclosedBy":{"name":"IrrQuery","type":"class"}},{"name":"kc_page","qualifiedName":"kc_page","href":"ui_session_flow_kc_page/ui_session_flow_kc_page-library.html","type":"library","overriddenDepth":0,"packageName":"chico_dagua"},{"name":"KcPage","qualifiedName":"kc_page.KcPage","href":"ui_session_flow_kc_page/KcPage-class.html","type":"class","overriddenDepth":0,"packageName":"chico_dagua","enclosedBy":{"name":"kc_page","type":"library"}},{"name":"operator ==","qualifiedName":"kc_page.KcPage.==","href":"ui_session_flow_kc_page/KcPage/operator_equals.html","type":"method","overriddenDepth":1,"packageName":"chico_dagua","enclosedBy":{"name":"KcPage","type":"class"}},{"name":"KcPage","qualifiedName":"kc_page.KcPage.KcPage","href":"ui_session_flow_kc_page/KcPage/KcPage.html","type":"constructor","overriddenDepth":0,"packageName":"chico_dagua","enclosedBy":{"name":"KcPage","type":"class"}},{"name":"createElement","qualifiedName":"kc_page.KcPage.createElement","href":"ui_session_flow_kc_page/KcPage/createElement.html","type":"method","overriddenDepth":1,"packageName":"chico_dagua","enclosedBy":{"name":"KcPage","type":"class"}},{"name":"createState","qualifiedName":"kc_page.KcPage.createState","href":"ui_session_flow_kc_page/KcPage/createState.html","type":"method","overriddenDepth":1,"packageName":"chico_dagua","enclosedBy":{"name":"KcPage","type":"class"}},{"name":"debugDescribeChildren","qualifiedName":"kc_page.KcPage.debugDescribeChildren","href":"ui_session_flow_kc_page/KcPage/debugDescribeChildren.html","type":"method","overriddenDepth":0,"packageName":"chico_dagua","enclosedBy":{"name":"KcPage","type":"class"}},{"name":"debugFillProperties","qualifiedName":"kc_page.KcPage.debugFillProperties","href":"ui_session_flow_kc_page/KcPage/debugFillProperties.html","type":"method","overriddenDepth":1,"packageName":"chico_dagua","enclosedBy":{"name":"KcPage","type":"class"}},{"name":"hashCode","qualifiedName":"kc_page.KcPage.hashCode","href":"ui_session_flow_kc_page/KcPage/hashCode.html","type":"property","overriddenDepth":0,"packageName":"chico_dagua","enclosedBy":{"name":"KcPage","type":"class"}},{"name":"key","qualifiedName":"kc_page.KcPage.key","href":"ui_session_flow_kc_page/KcPage/key.html","type":"property","overriddenDepth":0,"packageName":"chico_dagua","enclosedBy":{"name":"KcPage","type":"class"}},{"name":"toDiagnosticsNode","qualifiedName":"kc_page.KcPage.toDiagnosticsNode","href":"ui_session_flow_kc_page/KcPage/toDiagnosticsNode.html","type":"method","overriddenDepth":1,"packageName":"chico_dagua","enclosedBy":{"name":"KcPage","type":"class"}},{"name":"toString","qualifiedName":"kc_page.KcPage.toString","href":"ui_session_flow_kc_page/KcPage/toString.html","type":"method","overriddenDepth":1,"packageName":"chico_dagua","enclosedBy":{"name":"KcPage","type":"class"}},{"name":"toStringDeep","qualifiedName":"kc_page.KcPage.toStringDeep","href":"ui_session_flow_kc_page/KcPage/toStringDeep.html","type":"method","overriddenDepth":0,"packageName":"chico_dagua","enclosedBy":{"name":"KcPage","type":"class"}},{"name":"toStringShallow","qualifiedName":"kc_page.KcPage.toStringShallow","href":"ui_session_flow_kc_page/KcPage/toStringShallow.html","type":"method","overriddenDepth":0,"packageName":"chico_dagua","enclosedBy":{"name":"KcPage","type":"class"}},{"name":"toStringShort","qualifiedName":"kc_page.KcPage.toStringShort","href":"ui_session_flow_kc_page/KcPage/toStringShort.html","type":"method","overriddenDepth":2,"packageName":"chico_dagua","enclosedBy":{"name":"KcPage","type":"class"}},{"name":"kc_page_alt","qualifiedName":"kc_page_alt","href":"ui_session_flow_kc_page_alt/ui_session_flow_kc_page_alt-library.html","type":"library","overriddenDepth":0,"packageName":"chico_dagua"},{"name":"KcPageAlt","qualifiedName":"kc_page_alt.KcPageAlt","href":"ui_session_flow_kc_page_alt/KcPageAlt-class.html","type":"class","overriddenDepth":0,"packageName":"chico_dagua","enclosedBy":{"name":"kc_page_alt","type":"library"}},{"name":"operator ==","qualifiedName":"kc_page_alt.KcPageAlt.==","href":"ui_session_flow_kc_page_alt/KcPageAlt/operator_equals.html","type":"method","overriddenDepth":1,"packageName":"chico_dagua","enclosedBy":{"name":"KcPageAlt","type":"class"}},{"name":"KcPageAlt","qualifiedName":"kc_page_alt.KcPageAlt.KcPageAlt","href":"ui_session_flow_kc_page_alt/KcPageAlt/KcPageAlt.html","type":"constructor","overriddenDepth":0,"packageName":"chico_dagua","enclosedBy":{"name":"KcPageAlt","type":"class"}},{"name":"createElement","qualifiedName":"kc_page_alt.KcPageAlt.createElement","href":"ui_session_flow_kc_page_alt/KcPageAlt/createElement.html","type":"method","overriddenDepth":1,"packageName":"chico_dagua","enclosedBy":{"name":"KcPageAlt","type":"class"}},{"name":"createState","qualifiedName":"kc_page_alt.KcPageAlt.createState","href":"ui_session_flow_kc_page_alt/KcPageAlt/createState.html","type":"method","overriddenDepth":1,"packageName":"chico_dagua","enclosedBy":{"name":"KcPageAlt","type":"class"}},{"name":"debugDescribeChildren","qualifiedName":"kc_page_alt.KcPageAlt.debugDescribeChildren","href":"ui_session_flow_kc_page_alt/KcPageAlt/debugDescribeChildren.html","type":"method","overriddenDepth":0,"packageName":"chico_dagua","enclosedBy":{"name":"KcPageAlt","type":"class"}},{"name":"debugFillProperties","qualifiedName":"kc_page_alt.KcPageAlt.debugFillProperties","href":"ui_session_flow_kc_page_alt/KcPageAlt/debugFillProperties.html","type":"method","overriddenDepth":1,"packageName":"chico_dagua","enclosedBy":{"name":"KcPageAlt","type":"class"}},{"name":"hashCode","qualifiedName":"kc_page_alt.KcPageAlt.hashCode","href":"ui_session_flow_kc_page_alt/KcPageAlt/hashCode.html","type":"property","overriddenDepth":0,"packageName":"chico_dagua","enclosedBy":{"name":"KcPageAlt","type":"class"}},{"name":"key","qualifiedName":"kc_page_alt.KcPageAlt.key","href":"ui_session_flow_kc_page_alt/KcPageAlt/key.html","type":"property","overriddenDepth":0,"packageName":"chico_dagua","enclosedBy":{"name":"KcPageAlt","type":"class"}},{"name":"toDiagnosticsNode","qualifiedName":"kc_page_alt.KcPageAlt.toDiagnosticsNode","href":"ui_session_flow_kc_page_alt/KcPageAlt/toDiagnosticsNode.html","type":"method","overriddenDepth":1,"packageName":"chico_dagua","enclosedBy":{"name":"KcPageAlt","type":"class"}},{"name":"toString","qualifiedName":"kc_page_alt.KcPageAlt.toString","href":"ui_session_flow_kc_page_alt/KcPageAlt/toString.html","type":"method","overriddenDepth":1,"packageName":"chico_dagua","enclosedBy":{"name":"KcPageAlt","type":"class"}},{"name":"toStringDeep","qualifiedName":"kc_page_alt.KcPageAlt.toStringDeep","href":"ui_session_flow_kc_page_alt/KcPageAlt/toStringDeep.html","type":"method","overriddenDepth":0,"packageName":"chico_dagua","enclosedBy":{"name":"KcPageAlt","type":"class"}},{"name":"toStringShallow","qualifiedName":"kc_page_alt.KcPageAlt.toStringShallow","href":"ui_session_flow_kc_page_alt/KcPageAlt/toStringShallow.html","type":"method","overriddenDepth":0,"packageName":"chico_dagua","enclosedBy":{"name":"KcPageAlt","type":"class"}},{"name":"toStringShort","qualifiedName":"kc_page_alt.KcPageAlt.toStringShort","href":"ui_session_flow_kc_page_alt/KcPageAlt/toStringShort.html","type":"method","overriddenDepth":2,"packageName":"chico_dagua","enclosedBy":{"name":"KcPageAlt","type":"class"}},{"name":"loc_perm_page","qualifiedName":"loc_perm_page","href":"ui_initial_flow_loc_perm_page/ui_initial_flow_loc_perm_page-library.html","type":"library","overriddenDepth":0,"packageName":"chico_dagua"},{"name":"LocPermPage","qualifiedName":"loc_perm_page.LocPermPage","href":"ui_initial_flow_loc_perm_page/LocPermPage-class.html","type":"class","overriddenDepth":0,"packageName":"chico_dagua","enclosedBy":{"name":"loc_perm_page","type":"library"}},{"name":"operator ==","qualifiedName":"loc_perm_page.LocPermPage.==","href":"ui_initial_flow_loc_perm_page/LocPermPage/operator_equals.html","type":"method","overriddenDepth":1,"packageName":"chico_dagua","enclosedBy":{"name":"LocPermPage","type":"class"}},{"name":"LocPermPage","qualifiedName":"loc_perm_page.LocPermPage.LocPermPage","href":"ui_initial_flow_loc_perm_page/LocPermPage/LocPermPage.html","type":"constructor","overriddenDepth":0,"packageName":"chico_dagua","enclosedBy":{"name":"LocPermPage","type":"class"}},{"name":"build","qualifiedName":"loc_perm_page.LocPermPage.build","href":"ui_initial_flow_loc_perm_page/LocPermPage/build.html","type":"method","overriddenDepth":1,"packageName":"chico_dagua","enclosedBy":{"name":"LocPermPage","type":"class"}},{"name":"createElement","qualifiedName":"loc_perm_page.LocPermPage.createElement","href":"ui_initial_flow_loc_perm_page/LocPermPage/createElement.html","type":"method","overriddenDepth":1,"packageName":"chico_dagua","enclosedBy":{"name":"LocPermPage","type":"class"}},{"name":"debugDescribeChildren","qualifiedName":"loc_perm_page.LocPermPage.debugDescribeChildren","href":"ui_initial_flow_loc_perm_page/LocPermPage/debugDescribeChildren.html","type":"method","overriddenDepth":0,"packageName":"chico_dagua","enclosedBy":{"name":"LocPermPage","type":"class"}},{"name":"debugFillProperties","qualifiedName":"loc_perm_page.LocPermPage.debugFillProperties","href":"ui_initial_flow_loc_perm_page/LocPermPage/debugFillProperties.html","type":"method","overriddenDepth":1,"packageName":"chico_dagua","enclosedBy":{"name":"LocPermPage","type":"class"}},{"name":"ds","qualifiedName":"loc_perm_page.LocPermPage.ds","href":"ui_initial_flow_loc_perm_page/LocPermPage/ds.html","type":"property","overriddenDepth":0,"packageName":"chico_dagua","enclosedBy":{"name":"LocPermPage","type":"class"}},{"name":"hashCode","qualifiedName":"loc_perm_page.LocPermPage.hashCode","href":"ui_initial_flow_loc_perm_page/LocPermPage/hashCode.html","type":"property","overriddenDepth":0,"packageName":"chico_dagua","enclosedBy":{"name":"LocPermPage","type":"class"}},{"name":"key","qualifiedName":"loc_perm_page.LocPermPage.key","href":"ui_initial_flow_loc_perm_page/LocPermPage/key.html","type":"property","overriddenDepth":0,"packageName":"chico_dagua","enclosedBy":{"name":"LocPermPage","type":"class"}},{"name":"toDiagnosticsNode","qualifiedName":"loc_perm_page.LocPermPage.toDiagnosticsNode","href":"ui_initial_flow_loc_perm_page/LocPermPage/toDiagnosticsNode.html","type":"method","overriddenDepth":1,"packageName":"chico_dagua","enclosedBy":{"name":"LocPermPage","type":"class"}},{"name":"toString","qualifiedName":"loc_perm_page.LocPermPage.toString","href":"ui_initial_flow_loc_perm_page/LocPermPage/toString.html","type":"method","overriddenDepth":1,"packageName":"chico_dagua","enclosedBy":{"name":"LocPermPage","type":"class"}},{"name":"toStringDeep","qualifiedName":"loc_perm_page.LocPermPage.toStringDeep","href":"ui_initial_flow_loc_perm_page/LocPermPage/toStringDeep.html","type":"method","overriddenDepth":0,"packageName":"chico_dagua","enclosedBy":{"name":"LocPermPage","type":"class"}},{"name":"toStringShallow","qualifiedName":"loc_perm_page.LocPermPage.toStringShallow","href":"ui_initial_flow_loc_perm_page/LocPermPage/toStringShallow.html","type":"method","overriddenDepth":0,"packageName":"chico_dagua","enclosedBy":{"name":"LocPermPage","type":"class"}},{"name":"toStringShort","qualifiedName":"loc_perm_page.LocPermPage.toStringShort","href":"ui_initial_flow_loc_perm_page/LocPermPage/toStringShort.html","type":"method","overriddenDepth":2,"packageName":"chico_dagua","enclosedBy":{"name":"LocPermPage","type":"class"}},{"name":"main","qualifiedName":"main","href":"main/main-library.html","type":"library","overriddenDepth":0,"packageName":"chico_dagua"},{"name":"NewOne","qualifiedName":"main.NewOne","href":"main/NewOne-class.html","type":"class","overriddenDepth":0,"packageName":"chico_dagua","enclosedBy":{"name":"main","type":"library"}},{"name":"operator ==","qualifiedName":"main.NewOne.==","href":"main/NewOne/operator_equals.html","type":"method","overriddenDepth":1,"packageName":"chico_dagua","enclosedBy":{"name":"NewOne","type":"class"}},{"name":"NewOne","qualifiedName":"main.NewOne.NewOne","href":"main/NewOne/NewOne.html","type":"constructor","overriddenDepth":0,"packageName":"chico_dagua","enclosedBy":{"name":"NewOne","type":"class"}},{"name":"build","qualifiedName":"main.NewOne.build","href":"main/NewOne/build.html","type":"method","overriddenDepth":1,"packageName":"chico_dagua","enclosedBy":{"name":"NewOne","type":"class"}},{"name":"createElement","qualifiedName":"main.NewOne.createElement","href":"main/NewOne/createElement.html","type":"method","overriddenDepth":1,"packageName":"chico_dagua","enclosedBy":{"name":"NewOne","type":"class"}},{"name":"debugDescribeChildren","qualifiedName":"main.NewOne.debugDescribeChildren","href":"main/NewOne/debugDescribeChildren.html","type":"method","overriddenDepth":0,"packageName":"chico_dagua","enclosedBy":{"name":"NewOne","type":"class"}},{"name":"debugFillProperties","qualifiedName":"main.NewOne.debugFillProperties","href":"main/NewOne/debugFillProperties.html","type":"method","overriddenDepth":1,"packageName":"chico_dagua","enclosedBy":{"name":"NewOne","type":"class"}},{"name":"hashCode","qualifiedName":"main.NewOne.hashCode","href":"main/NewOne/hashCode.html","type":"property","overriddenDepth":0,"packageName":"chico_dagua","enclosedBy":{"name":"NewOne","type":"class"}},{"name":"key","qualifiedName":"main.NewOne.key","href":"main/NewOne/key.html","type":"property","overriddenDepth":0,"packageName":"chico_dagua","enclosedBy":{"name":"NewOne","type":"class"}},{"name":"themeData","qualifiedName":"main.NewOne.themeData","href":"main/NewOne/themeData.html","type":"method","overriddenDepth":0,"packageName":"chico_dagua","enclosedBy":{"name":"NewOne","type":"class"}},{"name":"toDiagnosticsNode","qualifiedName":"main.NewOne.toDiagnosticsNode","href":"main/NewOne/toDiagnosticsNode.html","type":"method","overriddenDepth":1,"packageName":"chico_dagua","enclosedBy":{"name":"NewOne","type":"class"}},{"name":"toString","qualifiedName":"main.NewOne.toString","href":"main/NewOne/toString.html","type":"method","overriddenDepth":1,"packageName":"chico_dagua","enclosedBy":{"name":"NewOne","type":"class"}},{"name":"toStringDeep","qualifiedName":"main.NewOne.toStringDeep","href":"main/NewOne/toStringDeep.html","type":"method","overriddenDepth":0,"packageName":"chico_dagua","enclosedBy":{"name":"NewOne","type":"class"}},{"name":"toStringShallow","qualifiedName":"main.NewOne.toStringShallow","href":"main/NewOne/toStringShallow.html","type":"method","overriddenDepth":0,"packageName":"chico_dagua","enclosedBy":{"name":"NewOne","type":"class"}},{"name":"toStringShort","qualifiedName":"main.NewOne.toStringShort","href":"main/NewOne/toStringShort.html","type":"method","overriddenDepth":2,"packageName":"chico_dagua","enclosedBy":{"name":"NewOne","type":"class"}},{"name":"main","qualifiedName":"main.main","href":"main/main.html","type":"function","overriddenDepth":0,"packageName":"chico_dagua","enclosedBy":{"name":"main","type":"library"}},{"name":"pos_loc_pre_cult","qualifiedName":"pos_loc_pre_cult","href":"ui_initial_flow_pos_loc_pre_cult/ui_initial_flow_pos_loc_pre_cult-library.html","type":"library","overriddenDepth":0,"packageName":"chico_dagua"},{"name":"PosLocPreCult","qualifiedName":"pos_loc_pre_cult.PosLocPreCult","href":"ui_initial_flow_pos_loc_pre_cult/PosLocPreCult-class.html","type":"class","overriddenDepth":0,"packageName":"chico_dagua","enclosedBy":{"name":"pos_loc_pre_cult","type":"library"}},{"name":"operator ==","qualifiedName":"pos_loc_pre_cult.PosLocPreCult.==","href":"ui_initial_flow_pos_loc_pre_cult/PosLocPreCult/operator_equals.html","type":"method","overriddenDepth":1,"packageName":"chico_dagua","enclosedBy":{"name":"PosLocPreCult","type":"class"}},{"name":"PosLocPreCult","qualifiedName":"pos_loc_pre_cult.PosLocPreCult.PosLocPreCult","href":"ui_initial_flow_pos_loc_pre_cult/PosLocPreCult/PosLocPreCult.html","type":"constructor","overriddenDepth":0,"packageName":"chico_dagua","enclosedBy":{"name":"PosLocPreCult","type":"class"}},{"name":"build","qualifiedName":"pos_loc_pre_cult.PosLocPreCult.build","href":"ui_initial_flow_pos_loc_pre_cult/PosLocPreCult/build.html","type":"method","overriddenDepth":1,"packageName":"chico_dagua","enclosedBy":{"name":"PosLocPreCult","type":"class"}},{"name":"createElement","qualifiedName":"pos_loc_pre_cult.PosLocPreCult.createElement","href":"ui_initial_flow_pos_loc_pre_cult/PosLocPreCult/createElement.html","type":"method","overriddenDepth":1,"packageName":"chico_dagua","enclosedBy":{"name":"PosLocPreCult","type":"class"}},{"name":"debugDescribeChildren","qualifiedName":"pos_loc_pre_cult.PosLocPreCult.debugDescribeChildren","href":"ui_initial_flow_pos_loc_pre_cult/PosLocPreCult/debugDescribeChildren.html","type":"method","overriddenDepth":0,"packageName":"chico_dagua","enclosedBy":{"name":"PosLocPreCult","type":"class"}},{"name":"debugFillProperties","qualifiedName":"pos_loc_pre_cult.PosLocPreCult.debugFillProperties","href":"ui_initial_flow_pos_loc_pre_cult/PosLocPreCult/debugFillProperties.html","type":"method","overriddenDepth":1,"packageName":"chico_dagua","enclosedBy":{"name":"PosLocPreCult","type":"class"}},{"name":"hashCode","qualifiedName":"pos_loc_pre_cult.PosLocPreCult.hashCode","href":"ui_initial_flow_pos_loc_pre_cult/PosLocPreCult/hashCode.html","type":"property","overriddenDepth":0,"packageName":"chico_dagua","enclosedBy":{"name":"PosLocPreCult","type":"class"}},{"name":"key","qualifiedName":"pos_loc_pre_cult.PosLocPreCult.key","href":"ui_initial_flow_pos_loc_pre_cult/PosLocPreCult/key.html","type":"property","overriddenDepth":0,"packageName":"chico_dagua","enclosedBy":{"name":"PosLocPreCult","type":"class"}},{"name":"toDiagnosticsNode","qualifiedName":"pos_loc_pre_cult.PosLocPreCult.toDiagnosticsNode","href":"ui_initial_flow_pos_loc_pre_cult/PosLocPreCult/toDiagnosticsNode.html","type":"method","overriddenDepth":1,"packageName":"chico_dagua","enclosedBy":{"name":"PosLocPreCult","type":"class"}},{"name":"toString","qualifiedName":"pos_loc_pre_cult.PosLocPreCult.toString","href":"ui_initial_flow_pos_loc_pre_cult/PosLocPreCult/toString.html","type":"method","overriddenDepth":1,"packageName":"chico_dagua","enclosedBy":{"name":"PosLocPreCult","type":"class"}},{"name":"toStringDeep","qualifiedName":"pos_loc_pre_cult.PosLocPreCult.toStringDeep","href":"ui_initial_flow_pos_loc_pre_cult/PosLocPreCult/toStringDeep.html","type":"method","overriddenDepth":0,"packageName":"chico_dagua","enclosedBy":{"name":"PosLocPreCult","type":"class"}},{"name":"toStringShallow","qualifiedName":"pos_loc_pre_cult.PosLocPreCult.toStringShallow","href":"ui_initial_flow_pos_loc_pre_cult/PosLocPreCult/toStringShallow.html","type":"method","overriddenDepth":0,"packageName":"chico_dagua","enclosedBy":{"name":"PosLocPreCult","type":"class"}},{"name":"toStringShort","qualifiedName":"pos_loc_pre_cult.PosLocPreCult.toStringShort","href":"ui_initial_flow_pos_loc_pre_cult/PosLocPreCult/toStringShort.html","type":"method","overriddenDepth":2,"packageName":"chico_dagua","enclosedBy":{"name":"PosLocPreCult","type":"class"}},{"name":"result_page","qualifiedName":"result_page","href":"ui_session_flow_result_page/ui_session_flow_result_page-library.html","type":"library","overriddenDepth":0,"packageName":"chico_dagua"},{"name":"ResultPage","qualifiedName":"result_page.ResultPage","href":"ui_session_flow_result_page/ResultPage-class.html","type":"class","overriddenDepth":0,"packageName":"chico_dagua","enclosedBy":{"name":"result_page","type":"library"}},{"name":"operator ==","qualifiedName":"result_page.ResultPage.==","href":"ui_session_flow_result_page/ResultPage/operator_equals.html","type":"method","overriddenDepth":1,"packageName":"chico_dagua","enclosedBy":{"name":"ResultPage","type":"class"}},{"name":"ResultPage","qualifiedName":"result_page.ResultPage.ResultPage","href":"ui_session_flow_result_page/ResultPage/ResultPage.html","type":"constructor","overriddenDepth":0,"packageName":"chico_dagua","enclosedBy":{"name":"ResultPage","type":"class"}},{"name":"createElement","qualifiedName":"result_page.ResultPage.createElement","href":"ui_session_flow_result_page/ResultPage/createElement.html","type":"method","overriddenDepth":1,"packageName":"chico_dagua","enclosedBy":{"name":"ResultPage","type":"class"}},{"name":"createState","qualifiedName":"result_page.ResultPage.createState","href":"ui_session_flow_result_page/ResultPage/createState.html","type":"method","overriddenDepth":1,"packageName":"chico_dagua","enclosedBy":{"name":"ResultPage","type":"class"}},{"name":"debugDescribeChildren","qualifiedName":"result_page.ResultPage.debugDescribeChildren","href":"ui_session_flow_result_page/ResultPage/debugDescribeChildren.html","type":"method","overriddenDepth":0,"packageName":"chico_dagua","enclosedBy":{"name":"ResultPage","type":"class"}},{"name":"debugFillProperties","qualifiedName":"result_page.ResultPage.debugFillProperties","href":"ui_session_flow_result_page/ResultPage/debugFillProperties.html","type":"method","overriddenDepth":1,"packageName":"chico_dagua","enclosedBy":{"name":"ResultPage","type":"class"}},{"name":"hashCode","qualifiedName":"result_page.ResultPage.hashCode","href":"ui_session_flow_result_page/ResultPage/hashCode.html","type":"property","overriddenDepth":0,"packageName":"chico_dagua","enclosedBy":{"name":"ResultPage","type":"class"}},{"name":"key","qualifiedName":"result_page.ResultPage.key","href":"ui_session_flow_result_page/ResultPage/key.html","type":"property","overriddenDepth":0,"packageName":"chico_dagua","enclosedBy":{"name":"ResultPage","type":"class"}},{"name":"toDiagnosticsNode","qualifiedName":"result_page.ResultPage.toDiagnosticsNode","href":"ui_session_flow_result_page/ResultPage/toDiagnosticsNode.html","type":"method","overriddenDepth":1,"packageName":"chico_dagua","enclosedBy":{"name":"ResultPage","type":"class"}},{"name":"toString","qualifiedName":"result_page.ResultPage.toString","href":"ui_session_flow_result_page/ResultPage/toString.html","type":"method","overriddenDepth":1,"packageName":"chico_dagua","enclosedBy":{"name":"ResultPage","type":"class"}},{"name":"toStringDeep","qualifiedName":"result_page.ResultPage.toStringDeep","href":"ui_session_flow_result_page/ResultPage/toStringDeep.html","type":"method","overriddenDepth":0,"packageName":"chico_dagua","enclosedBy":{"name":"ResultPage","type":"class"}},{"name":"toStringShallow","qualifiedName":"result_page.ResultPage.toStringShallow","href":"ui_session_flow_result_page/ResultPage/toStringShallow.html","type":"method","overriddenDepth":0,"packageName":"chico_dagua","enclosedBy":{"name":"ResultPage","type":"class"}},{"name":"toStringShort","qualifiedName":"result_page.ResultPage.toStringShort","href":"ui_session_flow_result_page/ResultPage/toStringShort.html","type":"method","overriddenDepth":2,"packageName":"chico_dagua","enclosedBy":{"name":"ResultPage","type":"class"}},{"name":"session_model","qualifiedName":"session_model","href":"model_session_model/model_session_model-library.html","type":"library","overriddenDepth":0,"packageName":"chico_dagua"},{"name":"SessionModel","qualifiedName":"session_model.SessionModel","href":"model_session_model/SessionModel-class.html","type":"class","overriddenDepth":0,"packageName":"chico_dagua","enclosedBy":{"name":"session_model","type":"library"}},{"name":"Eem","qualifiedName":"session_model.SessionModel.Eem","href":"model_session_model/SessionModel/Eem.html","type":"property","overriddenDepth":0,"packageName":"chico_dagua","enclosedBy":{"name":"SessionModel","type":"class"}},{"name":"El","qualifiedName":"session_model.SessionModel.El","href":"model_session_model/SessionModel/El.html","type":"property","overriddenDepth":0,"packageName":"chico_dagua","enclosedBy":{"name":"SessionModel","type":"class"}},{"name":"Ep","qualifiedName":"session_model.SessionModel.Ep","href":"model_session_model/SessionModel/Ep.html","type":"property","overriddenDepth":0,"packageName":"chico_dagua","enclosedBy":{"name":"SessionModel","type":"class"}},{"name":"SessionModel","qualifiedName":"session_model.SessionModel.SessionModel","href":"model_session_model/SessionModel/SessionModel.html","type":"constructor","overriddenDepth":0,"packageName":"chico_dagua","enclosedBy":{"name":"SessionModel","type":"class"}},{"name":"city","qualifiedName":"session_model.SessionModel.city","href":"model_session_model/SessionModel/city.html","type":"property","overriddenDepth":0,"packageName":"chico_dagua","enclosedBy":{"name":"SessionModel","type":"class"}},{"name":"cityId","qualifiedName":"session_model.SessionModel.cityId","href":"model_session_model/SessionModel/cityId.html","type":"property","overriddenDepth":0,"packageName":"chico_dagua","enclosedBy":{"name":"SessionModel","type":"class"}},{"name":"cultId","qualifiedName":"session_model.SessionModel.cultId","href":"model_session_model/SessionModel/cultId.html","type":"property","overriddenDepth":0,"packageName":"chico_dagua","enclosedBy":{"name":"SessionModel","type":"class"}},{"name":"cultName","qualifiedName":"session_model.SessionModel.cultName","href":"model_session_model/SessionModel/cultName.html","type":"property","overriddenDepth":0,"packageName":"chico_dagua","enclosedBy":{"name":"SessionModel","type":"class"}},{"name":"hasCity","qualifiedName":"session_model.SessionModel.hasCity","href":"model_session_model/SessionModel/hasCity.html","type":"property","overriddenDepth":0,"packageName":"chico_dagua","enclosedBy":{"name":"SessionModel","type":"class"}},{"name":"SessionModel.init","qualifiedName":"session_model.SessionModel.init","href":"model_session_model/SessionModel/SessionModel.init.html","type":"constructor","overriddenDepth":0,"packageName":"chico_dagua","enclosedBy":{"name":"SessionModel","type":"class"}},{"name":"lat","qualifiedName":"session_model.SessionModel.lat","href":"model_session_model/SessionModel/lat.html","type":"property","overriddenDepth":0,"packageName":"chico_dagua","enclosedBy":{"name":"SessionModel","type":"class"}},{"name":"of","qualifiedName":"session_model.SessionModel.of","href":"model_session_model/SessionModel/of.html","type":"method","overriddenDepth":0,"packageName":"chico_dagua","enclosedBy":{"name":"SessionModel","type":"class"}},{"name":"q","qualifiedName":"session_model.SessionModel.q","href":"model_session_model/SessionModel/q.html","type":"property","overriddenDepth":0,"packageName":"chico_dagua","enclosedBy":{"name":"SessionModel","type":"class"}},{"name":"setCity","qualifiedName":"session_model.SessionModel.setCity","href":"model_session_model/SessionModel/setCity.html","type":"method","overriddenDepth":0,"packageName":"chico_dagua","enclosedBy":{"name":"SessionModel","type":"class"}},{"name":"setCityId","qualifiedName":"session_model.SessionModel.setCityId","href":"model_session_model/SessionModel/setCityId.html","type":"method","overriddenDepth":0,"packageName":"chico_dagua","enclosedBy":{"name":"SessionModel","type":"class"}},{"name":"setCityState","qualifiedName":"session_model.SessionModel.setCityState","href":"model_session_model/SessionModel/setCityState.html","type":"method","overriddenDepth":0,"packageName":"chico_dagua","enclosedBy":{"name":"SessionModel","type":"class"}},{"name":"setCultId","qualifiedName":"session_model.SessionModel.setCultId","href":"model_session_model/SessionModel/setCultId.html","type":"method","overriddenDepth":0,"packageName":"chico_dagua","enclosedBy":{"name":"SessionModel","type":"class"}},{"name":"setCultName","qualifiedName":"session_model.SessionModel.setCultName","href":"model_session_model/SessionModel/setCultName.html","type":"method","overriddenDepth":0,"packageName":"chico_dagua","enclosedBy":{"name":"SessionModel","type":"class"}},{"name":"setEem","qualifiedName":"session_model.SessionModel.setEem","href":"model_session_model/SessionModel/setEem.html","type":"method","overriddenDepth":0,"packageName":"chico_dagua","enclosedBy":{"name":"SessionModel","type":"class"}},{"name":"setEl","qualifiedName":"session_model.SessionModel.setEl","href":"model_session_model/SessionModel/setEl.html","type":"method","overriddenDepth":0,"packageName":"chico_dagua","enclosedBy":{"name":"SessionModel","type":"class"}},{"name":"setEp","qualifiedName":"session_model.SessionModel.setEp","href":"model_session_model/SessionModel/setEp.html","type":"method","overriddenDepth":0,"packageName":"chico_dagua","enclosedBy":{"name":"SessionModel","type":"class"}},{"name":"setLat","qualifiedName":"session_model.SessionModel.setLat","href":"model_session_model/SessionModel/setLat.html","type":"method","overriddenDepth":0,"packageName":"chico_dagua","enclosedBy":{"name":"SessionModel","type":"class"}},{"name":"setState","qualifiedName":"session_model.SessionModel.setState","href":"model_session_model/SessionModel/setState.html","type":"method","overriddenDepth":0,"packageName":"chico_dagua","enclosedBy":{"name":"SessionModel","type":"class"}},{"name":"setq","qualifiedName":"session_model.SessionModel.setq","href":"model_session_model/SessionModel/setq.html","type":"method","overriddenDepth":0,"packageName":"chico_dagua","enclosedBy":{"name":"SessionModel","type":"class"}},{"name":"state","qualifiedName":"session_model.SessionModel.state","href":"model_session_model/SessionModel/state.html","type":"property","overriddenDepth":0,"packageName":"chico_dagua","enclosedBy":{"name":"SessionModel","type":"class"}},{"name":"toList","qualifiedName":"session_model.SessionModel.toList","href":"model_session_model/SessionModel/toList.html","type":"method","overriddenDepth":0,"packageName":"chico_dagua","enclosedBy":{"name":"SessionModel","type":"class"}},{"name":"work_page","qualifiedName":"work_page","href":"ui_work_page/ui_work_page-library.html","type":"library","overriddenDepth":0,"packageName":"chico_dagua"},{"name":"WorkPage","qualifiedName":"work_page.WorkPage","href":"ui_work_page/WorkPage-class.html","type":"class","overriddenDepth":0,"packageName":"chico_dagua","enclosedBy":{"name":"work_page","type":"library"}},{"name":"operator ==","qualifiedName":"work_page.WorkPage.==","href":"ui_work_page/WorkPage/operator_equals.html","type":"method","overriddenDepth":1,"packageName":"chico_dagua","enclosedBy":{"name":"WorkPage","type":"class"}},{"name":"WorkPage","qualifiedName":"work_page.WorkPage.WorkPage","href":"ui_work_page/WorkPage/WorkPage.html","type":"constructor","overriddenDepth":0,"packageName":"chico_dagua","enclosedBy":{"name":"WorkPage","type":"class"}},{"name":"createElement","qualifiedName":"work_page.WorkPage.createElement","href":"ui_work_page/WorkPage/createElement.html","type":"method","overriddenDepth":1,"packageName":"chico_dagua","enclosedBy":{"name":"WorkPage","type":"class"}},{"name":"createState","qualifiedName":"work_page.WorkPage.createState","href":"ui_work_page/WorkPage/createState.html","type":"method","overriddenDepth":1,"packageName":"chico_dagua","enclosedBy":{"name":"WorkPage","type":"class"}},{"name":"debugDescribeChildren","qualifiedName":"work_page.WorkPage.debugDescribeChildren","href":"ui_work_page/WorkPage/debugDescribeChildren.html","type":"method","overriddenDepth":0,"packageName":"chico_dagua","enclosedBy":{"name":"WorkPage","type":"class"}},{"name":"debugFillProperties","qualifiedName":"work_page.WorkPage.debugFillProperties","href":"ui_work_page/WorkPage/debugFillProperties.html","type":"method","overriddenDepth":1,"packageName":"chico_dagua","enclosedBy":{"name":"WorkPage","type":"class"}},{"name":"hashCode","qualifiedName":"work_page.WorkPage.hashCode","href":"ui_work_page/WorkPage/hashCode.html","type":"property","overriddenDepth":0,"packageName":"chico_dagua","enclosedBy":{"name":"WorkPage","type":"class"}},{"name":"key","qualifiedName":"work_page.WorkPage.key","href":"ui_work_page/WorkPage/key.html","type":"property","overriddenDepth":0,"packageName":"chico_dagua","enclosedBy":{"name":"WorkPage","type":"class"}},{"name":"toDiagnosticsNode","qualifiedName":"work_page.WorkPage.toDiagnosticsNode","href":"ui_work_page/WorkPage/toDiagnosticsNode.html","type":"method","overriddenDepth":1,"packageName":"chico_dagua","enclosedBy":{"name":"WorkPage","type":"class"}},{"name":"toString","qualifiedName":"work_page.WorkPage.toString","href":"ui_work_page/WorkPage/toString.html","type":"method","overriddenDepth":1,"packageName":"chico_dagua","enclosedBy":{"name":"WorkPage","type":"class"}},{"name":"toStringDeep","qualifiedName":"work_page.WorkPage.toStringDeep","href":"ui_work_page/WorkPage/toStringDeep.html","type":"method","overriddenDepth":0,"packageName":"chico_dagua","enclosedBy":{"name":"WorkPage","type":"class"}},{"name":"toStringShallow","qualifiedName":"work_page.WorkPage.toStringShallow","href":"ui_work_page/WorkPage/toStringShallow.html","type":"method","overriddenDepth":0,"packageName":"chico_dagua","enclosedBy":{"name":"WorkPage","type":"class"}},{"name":"toStringShort","qualifiedName":"work_page.WorkPage.toStringShort","href":"ui_work_page/WorkPage/toStringShort.html","type":"method","overriddenDepth":2,"packageName":"chico_dagua","enclosedBy":{"name":"WorkPage","type":"class"}}]
